README.md
setup.cfg
setup.py
prometheus_express/__init__.py
prometheus_express/metric.py
prometheus_express/registry.py
prometheus_express/router.py
prometheus_express/server.py
prometheus_express/utils.py
prometheus_express.egg-info/PKG-INFO
prometheus_express.egg-info/SOURCES.txt
prometheus_express.egg-info/dependency_links.txt
prometheus_express.egg-info/top_level.txt