Metadata-Version: 2.1
Name: prometheus-express
Version: 0.0.4
Summary: Prometheus SDK for CircuitPython Express ARM devices
Home-page: https://github.com/ssube/prometheus_express
Author: Sean Sube
Author-email: seansube@gmail.com
License: UNKNOWN
Keywords: prometheus
Platform: UNKNOWN
Classifier: Programming Language :: Python :: 3
Classifier: License :: OSI Approved :: MIT License
Classifier: Operating System :: OS Independent
Requires-Python: >=3.0
